{
    "key": "group_62af799fa840b",
    "title": "Firestarter",
    "fields": [
        {
            "key": "field_62af7b3fa5cb5",
            "label": "Site",
            "name": "site",
            "type": "group",
            "instructions": "",
            "required": 0,
            "conditional_logic": 0,
            "wrapper": {
                "width": "",
                "class": "",
                "id": ""
            },
            "layout": "block",
            "sub_fields": [
                {
                    "key": "field_6347e65e6cb12",
                    "label": "Theme: General Settings",
                    "name": "",
                    "type": "tab",
                    "instructions": "",
                    "required": 0,
                    "conditional_logic": 0,
                    "wrapper": {
                        "width": "",
                        "class": "",
                        "id": ""
                    },
                    "placement": "left",
                    "endpoint": 0
                },
                {
                    "key": "field_62af79bb302d7",
                    "label": "Logo",
                    "name": "logo",
                    "type": "image",
                    "instructions": "",
                    "required": 0,
                    "conditional_logic": 0,
                    "wrapper": {
                        "width": "",
                        "class": "",
                        "id": ""
                    },
                    "return_format": "id",
                    "preview_size": "thumbnail",
                    "library": "all",
                    "min_width": "",
                    "min_height": "",
                    "min_size": "",
                    "max_width": "",
                    "max_height": "",
                    "max_size": "",
                    "mime_types": ""
                },
                {
                    "key": "field_62af79d6302d8",
                    "label": "Logo @2x",
                    "name": "logo_2x",
                    "type": "image",
                    "instructions": "",
                    "required": 0,
                    "conditional_logic": 0,
                    "wrapper": {
                        "width": "",
                        "class": "",
                        "id": ""
                    },
                    "return_format": "id",
                    "preview_size": "thumbnail",
                    "library": "all",
                    "min_width": "",
                    "min_height": "",
                    "min_size": "",
                    "max_width": "",
                    "max_height": "",
                    "max_size": "",
                    "mime_types": ""
                },
                {
                    "key": "field_62b42b9709181",
                    "label": "Copyrights",
                    "name": "copyrights",
                    "type": "text",
                    "instructions": "",
                    "required": 0,
                    "conditional_logic": 0,
                    "wrapper": {
                        "width": "",
                        "class": "",
                        "id": ""
                    },
                    "default_value": "",
                    "placeholder": "",
                    "prepend": "",
                    "append": "",
                    "maxlength": ""
                },
                {
                    "key": "field_6347e6756cb13",
                    "label": "Theme: Media Settings",
                    "name": "",
                    "type": "tab",
                    "instructions": "",
                    "required": 0,
                    "conditional_logic": 0,
                    "wrapper": {
                        "width": "",
                        "class": "",
                        "id": ""
                    },
                    "placement": "left",
                    "endpoint": 0
                },
                {
                    "key": "field_6347e6d46cb14",
                    "label": "Generate WEBP",
                    "name": "webp_images",
                    "type": "true_false",
                    "instructions": "The module generates the webp version of the uploaded images. Please remember that it is not fully supported in modern browsers. It also requires special entries added in .htaccess.",
                    "required": 0,
                    "conditional_logic": 0,
                    "wrapper": {
                        "width": "",
                        "class": "",
                        "id": ""
                    },
                    "message": "",
                    "default_value": 0,
                    "ui": 1,
                    "ui_on_text": "Enabled",
                    "ui_off_text": "Disabled"
                }
            ]
        }
    ],
    "location": [
        [
            {
                "param": "options_page",
                "operator": "==",
                "value": "firestarter"
            }
        ]
    ],
    "menu_order": 0,
    "position": "normal",
    "style": "default",
    "label_placement": "top",
    "instruction_placement": "label",
    "hide_on_screen": "",
    "active": true,
    "description": "",
    "show_in_rest": 0,
    "modified": 1665731698
}